{
 "SoundBanksInfo": {
  "Platform": "Mac",
  "BasePlatform": "Mac",
  "SchemaVersion": "16",
  "SoundBankVersion": "154",
  "SoundBanks": [
   {
    "Id": "393239870",
    "Type": "User",
    "GUID": "{B698D3A4-E270-4037-91B1-84932FA778CA}",
    "Language": "SFX",
    "Hash": "{C268B6F3-E254-9991-E74A-44AE40A4E81D}",
    "ObjectPath": "\\SoundBanks\\Default Work Unit\\SFX",
    "ShortName": "SFX",
    "Path": "SFX.bnk",
    "Media": [
     {
      "Id": "71480746",
      "Language": "SFX",
      "Streaming": "false",
      "Location": "Memory",
      "ShortName": "Main Menu_Buttons-04.wav",
      "CachePath": "CA/{CA44770F-1771-B69D-9D1A-694098FF9093}.wem"
     },
     {
      "Id": "163824791",
      "Language": "SFX",
      "Streaming": "false",
      "Location": "Memory",
      "ShortName": "Puzzle Mechanic_Blink Sound 2-01.wav",
      "CachePath": "5E/{5EBB2054-0E32-C28C-F563-C03EC1181614}.wem"
     },
     {
      "Id": "250890795",
      "Language": "SFX",
      "Streaming": "false",
      "Location": "Memory",
      "ShortName": "VEHBus_Bus Constant_2.wav",
      "CachePath": "17/{17986ABD-5501-8C55-D080-209405B6CB6E}.wem"
     },
     {
      "Id": "267739961",
      "Language": "SFX",
      "Streaming": "false",
      "Location": "Memory",
      "ShortName": "Puzzle Mechanic_Completion Puzzle Lights Sound 4.wav",
      "CachePath": "05/{05B2272F-EB1A-AD0A-A91A-E99992845B15}.wem"
     },
     {
      "Id": "298126571",
      "Language": "SFX",
      "Streaming": "false",
      "Location": "Memory",
      "ShortName": "Main Menu_Buttons-08.wav",
      "CachePath": "D2/{D26BD2F2-EB0F-C1A9-19BE-99CF9CBEA80A}.wem"
     },
     {
      "Id": "374551954",
      "Language": "SFX",
      "Streaming": "false",
      "Location": "Memory",
      "ShortName": "Puzzle Mechanic_Completion Puzzle Lights Sound 2.wav",
      "CachePath": "4B/{4B6995E0-C7A3-842E-059E-F2C79D706D4E}.wem"
     },
     {
      "Id": "467324457",
      "Language": "SFX",
      "Streaming": "false",
      "Location": "Memory",
      "ShortName": "Puzzle Mechanic_Completion Puzzle Lights Sound 3.wav",
      "CachePath": "9E/{9EE2D2AC-9F9D-6409-AA27-16838B041501}.wem"
     },
     {
      "Id": "524855920",
      "Language": "SFX",
      "Streaming": "false",
      "Location": "Memory",
      "ShortName": "Puzzle Mechanic_Blink Sound 1-01.wav",
      "CachePath": "B3/{B376E8DB-CA51-B283-3D1A-615DC2F26487}.wem"
     },
     {
      "Id": "608203091",
      "Language": "SFX",
      "Streaming": "false",
      "Location": "Memory",
      "ShortName": "Puzzle Mechanic_Completion Puzzle Lights Sound 5.wav",
      "CachePath": "CD/{CD6DAF84-4516-B275-D864-63EDD3EFA7B4}.wem"
     },
     {
      "Id": "635014400",
      "Language": "SFX",
      "Streaming": "false",
      "Location": "Memory",
      "ShortName": "Puzzle Mechanic_Completion Puzzle Lights Sound 1.wav",
      "CachePath": "3E/{3E52DF97-6622-0401-9A33-823C8CF17D65}.wem"
     },
     {
      "Id": "643726567",
      "Language": "SFX",
      "Streaming": "false",
      "Location": "Memory",
      "ShortName": "Main Menu_Buttons-10.wav",
      "CachePath": "F4/{F409C778-1939-89DE-BC6D-A9BB343BE4F9}.wem"
     },
     {
      "Id": "673495175",
      "Language": "SFX",
      "Streaming": "false",
      "Location": "Memory",
      "ShortName": "UIAlert_Pop_Up.wav",
      "CachePath": "EA/{EA6FE200-0DF2-D6A2-91B1-2ECD1A9BFD8B}.wem"
     },
     {
      "Id": "809242091",
      "Language": "SFX",
      "Streaming": "false",
      "Location": "Memory",
      "ShortName": "VEHBus_Bus Constant_1.wav",
      "CachePath": "C5/{C5730964-CD17-805F-0575-D637FB57512C}.wem"
     },
     {
      "Id": "864253250",
      "Language": "SFX",
      "Streaming": "false",
      "Location": "Memory",
      "ShortName": "Main Menu_Buttons-02.wav",
      "CachePath": "9A/{9A828280-1648-81F8-86B5-0EB97D157056}.wem"
     },
     {
      "Id": "925688331",
      "Language": "SFX",
      "Streaming": "false",
      "Location": "Memory",
      "ShortName": "Puzzle Mechanic_Pick Up sound.wav",
      "CachePath": "CB/{CB73EE08-FFDD-AAEF-5C6A-5A6B5D7450F4}.wem"
     },
     {
      "Id": "947028516",
      "Language": "SFX",
      "Streaming": "false",
      "Location": "Memory",
      "ShortName": "Puzzle Mechanic_Rotation Sound.wav",
      "CachePath": "6C/{6C59D0F2-F4E7-0D50-DBDF-74734166661D}.wem"
     },
     {
      "Id": "950039673",
      "Language": "SFX",
      "Streaming": "false",
      "Location": "Memory",
      "ShortName": "Puzzle Mechanic_Drop sound.wav",
      "CachePath": "71/{71DBD29C-510E-4D92-B13C-18C7336A079C}.wem"
     },
     {
      "Id": "970725993",
      "Language": "SFX",
      "Streaming": "false",
      "Location": "Memory",
      "ShortName": "Main Menu_Buttons-06.wav",
      "CachePath": "44/{44BD1919-ECAC-9365-3371-65DF6482C100}.wem"
     }
    ],
    "Events": [
     {
      "Id": "650913174",
      "Name": "Bus_PlayConstant",
      "ObjectPath": "\\Events\\ATM\\Bus Int\\Bus_PlayConstant",
      "GUID": "{F15D593B-D074-405F-AF82-3D1BE54882F1}",
      "DurationType": "OneShot",
      "DurationMin": "187.21066",
      "DurationMax": "187.21066",
      "MediaRefs": [
       {
        "Id": "809242091"
       }
      ]
     },
     {
      "Id": "2841586448",
      "Name": "Bus_PlayConstant2",
      "ObjectPath": "\\Events\\ATM\\Bus Int\\Bus_PlayConstant2",
      "GUID": "{DD722AD0-ABEE-430A-ACC0-4282A5BD91E2}",
      "DurationType": "OneShot",
      "DurationMin": "183.38133",
      "DurationMax": "183.38133",
      "MediaRefs": [
       {
        "Id": "250890795"
       }
      ]
     },
     {
      "Id": "1216243508",
      "Name": "Bus_StopConstant",
      "ObjectPath": "\\Events\\ATM\\Bus Int\\Bus_StopConstant",
      "GUID": "{6753EE6B-156F-4144-B32A-D55142320BE4}",
      "MaxAttenuation": "0",
      "DurationType": "OneShot",
      "DurationMin": "0",
      "DurationMax": "0"
     },
     {
      "Id": "1392277230",
      "Name": "Bus_StopConstant2",
      "ObjectPath": "\\Events\\ATM\\Bus Int\\Bus_StopConstant2",
      "GUID": "{37E38019-511F-4816-8568-CF8D5A5E33A8}",
      "MaxAttenuation": "0",
      "DurationType": "OneShot",
      "DurationMin": "0",
      "DurationMax": "0"
     },
     {
      "Id": "777890284",
      "Name": "MainMenu_Play",
      "ObjectPath": "\\Events\\UI\\Menu\\MainMenu_Play",
      "GUID": "{6315C09B-4757-448A-83D9-5F65328A40CD}",
      "DurationType": "OneShot",
      "DurationMin": "0.1046875",
      "DurationMax": "0.23535417",
      "MediaRefs": [
       {
        "Id": "71480746"
       },
       {
        "Id": "298126571"
       },
       {
        "Id": "643726567"
       },
       {
        "Id": "864253250"
       },
       {
        "Id": "970725993"
       }
      ]
     },
     {
      "Id": "2122616712",
      "Name": "Puzzle_PlayBlink",
      "ObjectPath": "\\Events\\UI\\Puzzle\\Puzzle_PlayBlink",
      "GUID": "{3F411BB5-5124-4AD0-B7CC-E0917024B231}",
      "DurationType": "OneShot",
      "DurationMin": "10.629979",
      "DurationMax": "10.629979",
      "MediaRefs": [
       {
        "Id": "524855920"
       }
      ]
     },
     {
      "Id": "2997744426",
      "Name": "Puzzle_PlayBlink2",
      "ObjectPath": "\\Events\\UI\\Puzzle\\Puzzle_PlayBlink2",
      "GUID": "{CD18E3F3-81C5-47AD-BF63-24ABC3F7EEC4}",
      "DurationType": "OneShot",
      "DurationMin": "4.3153334",
      "DurationMax": "4.3153334",
      "MediaRefs": [
       {
        "Id": "163824791"
       }
      ]
     },
     {
      "Id": "3493478672",
      "Name": "Puzzle_PlayCompletion",
      "ObjectPath": "\\Events\\UI\\Puzzle\\Puzzle_PlayCompletion",
      "GUID": "{1A887FFA-6CB4-4C98-B63D-319DC7A5EF4E}",
      "DurationType": "OneShot",
      "DurationMin": "2.7652292",
      "DurationMax": "2.7652292",
      "MediaRefs": [
       {
        "Id": "635014400"
       }
      ]
     },
     {
      "Id": "3686034434",
      "Name": "Puzzle_PlayCompletion2",
      "ObjectPath": "\\Events\\UI\\Puzzle\\Puzzle_PlayCompletion2",
      "GUID": "{22A7D1C2-6E31-4114-A851-7427728080D6}",
      "DurationType": "OneShot",
      "DurationMin": "2.691729",
      "DurationMax": "2.691729",
      "MediaRefs": [
       {
        "Id": "374551954"
       }
      ]
     },
     {
      "Id": "3686034435",
      "Name": "Puzzle_PlayCompletion3",
      "ObjectPath": "\\Events\\UI\\Puzzle\\Puzzle_PlayCompletion3",
      "GUID": "{1FA852FF-9D22-4C64-B3B4-666FB2B84729}",
      "DurationType": "OneShot",
      "DurationMin": "1.4070417",
      "DurationMax": "1.4070417",
      "MediaRefs": [
       {
        "Id": "467324457"
       }
      ]
     },
     {
      "Id": "3686034436",
      "Name": "Puzzle_PlayCompletion4",
      "ObjectPath": "\\Events\\UI\\Puzzle\\Puzzle_PlayCompletion4",
      "GUID": "{78F1A261-5F56-4329-8CCA-71CD4361F435}",
      "DurationType": "OneShot",
      "DurationMin": "3.303146",
      "DurationMax": "3.303146",
      "MediaRefs": [
       {
        "Id": "267739961"
       }
      ]
     },
     {
      "Id": "3686034437",
      "Name": "Puzzle_PlayCompletion5",
      "ObjectPath": "\\Events\\UI\\Puzzle\\Puzzle_PlayCompletion5",
      "GUID": "{3D0F6A3E-6A95-4BD5-B3F3-B161060EA86B}",
      "DurationType": "OneShot",
      "DurationMin": "3.4743958",
      "DurationMax": "3.4743958",
      "MediaRefs": [
       {
        "Id": "608203091"
       }
      ]
     },
     {
      "Id": "699607909",
      "Name": "Puzzle_PlayDrop",
      "ObjectPath": "\\Events\\UI\\Puzzle\\Puzzle_PlayDrop",
      "GUID": "{56BDD7CD-94E1-4ED4-B8BB-7C4995FF73B4}",
      "DurationType": "OneShot",
      "DurationMin": "0.086958334",
      "DurationMax": "0.086958334",
      "MediaRefs": [
       {
        "Id": "950039673"
       }
      ]
     },
     {
      "Id": "528779466",
      "Name": "Puzzle_PlayPickUp",
      "ObjectPath": "\\Events\\UI\\Puzzle\\Puzzle_PlayPickUp",
      "GUID": "{B6D83DAA-B4F7-446A-BC06-EECD98C6264C}",
      "DurationType": "OneShot",
      "DurationMin": "0.070083335",
      "DurationMax": "0.070083335",
      "MediaRefs": [
       {
        "Id": "925688331"
       }
      ]
     },
     {
      "Id": "1911763448",
      "Name": "Puzzle_PlayRotation",
      "ObjectPath": "\\Events\\UI\\Puzzle\\Puzzle_PlayRotation",
      "GUID": "{B8FCC2DF-002E-407D-96D1-D96D5D2CCCE9}",
      "DurationType": "OneShot",
      "DurationMin": "0.34675",
      "DurationMax": "0.34675",
      "MediaRefs": [
       {
        "Id": "947028516"
       }
      ]
     },
     {
      "Id": "4040085034",
      "Name": "Puzzle_StopBlink",
      "ObjectPath": "\\Events\\UI\\Puzzle\\Puzzle_StopBlink",
      "GUID": "{FB2C8B83-DF04-4020-A729-2CE49FEA65CA}",
      "MaxAttenuation": "0",
      "DurationType": "OneShot",
      "DurationMin": "0",
      "DurationMax": "0"
     },
     {
      "Id": "1066306604",
      "Name": "Puzzle_StopBlink2",
      "ObjectPath": "\\Events\\UI\\Puzzle\\Puzzle_StopBlink2",
      "GUID": "{9380F85A-6EA1-4CA9-BD83-532516AE6083}",
      "MaxAttenuation": "0",
      "DurationType": "OneShot",
      "DurationMin": "0",
      "DurationMax": "0"
     },
     {
      "Id": "434496694",
      "Name": "UI_PlayPopUp",
      "ObjectPath": "\\Events\\UI\\UI_PlayPopUp",
      "GUID": "{C4F4645C-335C-416F-B246-E8CE11D0A2FE}",
      "DurationType": "OneShot",
      "DurationMin": "0.24727084",
      "DurationMax": "0.24727084",
      "MediaRefs": [
       {
        "Id": "673495175"
       }
      ]
     }
    ]
   }
  ],
  "FileHash": "{F238B082-79EF-561D-CC98-47124418839C}"
 }
}